dbplot/__init__.py
dbplot/_version.py
dbplot/calculations.py
dbplot/mpl.py
dbplot-0.1.0.dist-info/LICENSE
dbplot-0.1.0.dist-info/WHEEL
dbplot-0.1.0.dist-info/METADATA
dbplot-0.1.0.dist-info/RECORD
